minpack_numba-0.1.0.dist-info/METADATA
minpack_numba-0.1.0.dist-info/WHEEL
minpack_numba-0.1.0.dist-info/LICENSE
minpack_numba/libminpack.dylib
minpack_numba/__init__.py
minpack_numba/_minpack.py
minpack_numba/bounds.py
minpack_numba/chkder.py
minpack_numba/dpmpar.py
minpack_numba/hybrd.py
minpack_numba/hybrj.py
minpack_numba/lmder.py
minpack_numba/lmdif.py
minpack_numba/lmstr.py
minpack_numba/signatures.py
minpack_numba/utils.py
minpack_numba-0.1.0.data/headers/minpack.h
minpack_numba-0.1.0.dist-info/RECORD
