Metadata-Version: 2.1
Name: minpack-numba
Version: 0.1.0
Summary: A numba compatible wrapper of modern minpack.
Author-Email: Chris Ninham <christopher.ninham@insa-lyon.fr>
License: MIT License
Requires-Dist: numba
Requires-Dist: numpy
Provides-Extra: dev
Requires-Dist: pytest; extra == "dev"
Requires-Dist: pytest-env; extra == "dev"
Requires-Dist: ruff; extra == "dev"
Requires-Dist: scipy; extra == "dev"
